[{"name": "In The Waves", "artist": "Yeonjeong", "song_url": "https://www.last.fm/music/Yeonjeong/_/In+The+Waves", "artist_url": "https://www.last.fm/music/Yeonjeong"},{"name": "Lovin' Me", "artist": "Fifty Fifty", "song_url": "https://www.last.fm/music/Fifty+Fifty/_/Lovin%27+Me", "artist_url": "https://www.last.fm/music/Fifty+Fifty"},{"name": "Tell Me", "artist": "Fifty Fifty", "song_url": "https://www.last.fm/music/Fifty+Fifty/_/Tell+Me", "artist_url": "https://www.last.fm/music/Fifty+Fifty"},{"name": "Bridget St. John", "artist": "Hamish Hawk", "song_url": "https://www.last.fm/music/Hamish+Hawk/_/Bridget+St.+John", "artist_url": "https://www.last.fm/music/Hamish+Hawk"},{"name": "Young Man", "artist": "HYUKOH", "song_url": "https://www.last.fm/music/HYUKOH/_/Young+Man", "artist_url": "https://www.last.fm/music/HYUKOH"}]