[{"name": "ENEMY", "artist": "TWICE", "song_url": "https://www.last.fm/music/TWICE/_/ENEMY", "artist_url": "https://www.last.fm/music/TWICE"},{"name": "In The Waves", "artist": "Yeonjeong", "song_url": "https://www.last.fm/music/Yeonjeong/_/In+The+Waves", "artist_url": "https://www.last.fm/music/Yeonjeong"},{"name": "JUMP", "artist": "BLACKPINK", "song_url": "https://www.last.fm/music/BLACKPINK/_/JUMP", "artist_url": "https://www.last.fm/music/BLACKPINK"},{"name": "Power Station", "artist": "Cory Wong", "song_url": "https://www.last.fm/music/Cory+Wong/_/Power+Station", "artist_url": "https://www.last.fm/music/Cory+Wong"},{"name": "Concrete", "artist": "Cory Wong", "song_url": "https://www.last.fm/music/Cory+Wong/_/Concrete", "artist_url": "https://www.last.fm/music/Cory+Wong"}]