[{"name": "夏霞", "artist": "あたらよ", "song_url": "https://www.last.fm/music/%E3%81%82%E3%81%9F%E3%82%89%E3%82%88/_/%E5%A4%8F%E9%9C%9E", "artist_url": "https://www.last.fm/music/%E3%81%82%E3%81%9F%E3%82%89%E3%82%88"},{"name": "Romain - Alt. Take", "artist": "Bill Evans", "song_url": "https://www.last.fm/music/Bill+Evans/_/Romain+-+Alt.+Take", "artist_url": "https://www.last.fm/music/Bill+Evans"},{"name": "À peu près", "artist": "Pomme", "song_url": "https://www.last.fm/music/Pomme/_/%C3%80+peu+pr%C3%A8s", "artist_url": "https://www.last.fm/music/Pomme"},{"name": "Des pas dans la neige", "artist": "Clio", "song_url": "https://www.last.fm/music/Clio/_/Des+pas+dans+la+neige", "artist_url": "https://www.last.fm/music/Clio"},{"name": "TELL THE TRUTH", "artist": "Jon Batiste", "song_url": "https://www.last.fm/music/Jon+Batiste/_/TELL+THE+TRUTH", "artist_url": "https://www.last.fm/music/Jon+Batiste"},{"name": "10月無口な君を忘れる", "artist": "あたらよ", "song_url": "https://www.last.fm/music/%E3%81%82%E3%81%9F%E3%82%89%E3%82%88/_/10%E6%9C%88%E7%84%A1%E5%8F%A3%E3%81%AA%E5%90%9B%E3%82%92%E5%BF%98%E3%82%8C%E3%82%8B", "artist_url": "https://www.last.fm/music/%E3%81%82%E3%81%9F%E3%82%89%E3%82%88"},{"name": "極夜", "artist": "あたらよ", "song_url": "https://www.last.fm/music/%E3%81%82%E3%81%9F%E3%82%89%E3%82%88/_/%E6%A5%B5%E5%A4%9C", "artist_url": "https://www.last.fm/music/%E3%81%82%E3%81%9F%E3%82%89%E3%82%88"},{"name": "帶你飛", "artist": "告五人", "song_url": "https://www.last.fm/music/%E5%91%8A%E4%BA%94%E4%BA%BA/_/%E5%B8%B6%E4%BD%A0%E9%A3%9B", "artist_url": "https://www.last.fm/music/%E5%91%8A%E4%BA%94%E4%BA%BA"},{"name": "我想要佔據你", "artist": "告五人", "song_url": "https://www.last.fm/music/%E5%91%8A%E4%BA%94%E4%BA%BA/_/%E6%88%91%E6%83%B3%E8%A6%81%E4%BD%94%E6%93%9A%E4%BD%A0", "artist_url": "https://www.last.fm/music/%E5%91%8A%E4%BA%94%E4%BA%BA"},{"name": "One", "artist": "Aimer", "song_url": "https://www.last.fm/music/Aimer/_/One", "artist_url": "https://www.last.fm/music/Aimer"}]